scmail-1.0.9.data/scripts/run_scmail.py
scmail-1.0.9.data/scripts/scmail_tests.py
scmail_libs/EM_solver.py
scmail_libs/ML_solver.py
scmail_libs/SpaLin_solver.py
scmail_libs/Topology_search.py
scmail_libs/Topology_search_parallel.py
scmail_libs/Virtual_solver.py
scmail_libs/__init__.py
scmail_libs/distance_based_lib.py
scmail_libs/eval_lib.py
scmail_libs/lca_lib.py
scmail_libs/plot_lib.py
scmail_libs/sequence_lib.py
scmail_libs/sim_lib.py
scmail_unit_tests/__init__.py
scmail_unit_tests/unit_tests_EMSolver.py
scmail_unit_tests/unit_tests_MLSolver.py
scmail_unit_tests/unit_tests_Simulator.py
scmail_unit_tests/unit_tests_SpaLinSolver.py
scmail_unit_tests/unit_tests_TopoSearch.py
scmail_unit_tests/unit_tests_TopoSearchParallel.py
scmail_unit_tests/utils.py
scmail_unit_tests/test_data/test_EM/test1.tre
scmail_unit_tests/test_data/test_EM/test1_charMtrx.txt
scmail_unit_tests/test_data/test_EM/test2.tre
scmail_unit_tests/test_data/test_EM/test2_charMtrx.txt
scmail_unit_tests/test_data/test_EM/test3.tre
scmail_unit_tests/test_data/test_EM/test3_charMtrx.txt
scmail_unit_tests/test_data/test_EM/test4.tre
scmail_unit_tests/test_data/test_EM/test4_charMtrx.txt
scmail_unit_tests/test_data/test_EM/test4_prior.csv
scmail_unit_tests/test_data/test_simulator/test.tre
scmail-1.0.9.dist-info/LICENSE
scmail-1.0.9.dist-info/METADATA
scmail-1.0.9.dist-info/WHEEL
scmail-1.0.9.dist-info/entry_points.txt
scmail-1.0.9.dist-info/top_level.txt
scmail-1.0.9.dist-info/zip-safe
scmail-1.0.9.dist-info/RECORD
