Metadata-Version: 2.1
Name: scmail
Version: 1.0.9
Summary: sc-MAIL: single-cell Maximum-likelihood Ancestral Inference for Lineage-tracing
Author: ['Uyen Mai', 'Gillian Chu', 'Ben Raphael']
License: GNU General Public License, version 3
Keywords: Phylogenetics Evolution Computational Maximum-likelihood Single-cell Lineage Tracing
Classifier: Environment :: Console
Classifier: Intended Audience :: Developers
Classifier: Intended Audience :: Science/Research
Classifier: License :: OSI Approved :: GNU General Public License (GPL)
Classifier: Natural Language :: English
Classifier: Operating System :: OS Independent
Classifier: Programming Language :: Python
Classifier: Topic :: Scientific/Engineering :: Bio-Informatics
License-File: LICENSE
Requires-Dist: numpy (>=1.16)
Requires-Dist: treeswift (>=1.1.37)
Requires-Dist: scipy (>=1.3.1)
Requires-Dist: cvxpy (>=1.4)
Requires-Dist: Mosek (>=10.1.16)
Requires-Dist: cmake (>=3.18.0)
Requires-Dist: setuptools
